lmstrix/__init__.py
lmstrix/__main__.py
lmstrix/_version.py
lmstrix/py.typed
lmstrix/api/__init__.py
lmstrix/api/client.py
lmstrix/api/exceptions.py
lmstrix/api/main.py
lmstrix/core/__init__.py
lmstrix/core/concrete_config.py
lmstrix/core/context.py
lmstrix/core/context_tester.py
lmstrix/core/inference.py
lmstrix/core/inference_manager.py
lmstrix/core/models.py
lmstrix/core/prompts.py
lmstrix/core/scanner.py
lmstrix/loaders/__init__.py
lmstrix/loaders/context_loader.py
lmstrix/loaders/model_loader.py
lmstrix/loaders/prompt_loader.py
lmstrix/utils/__init__.py
lmstrix/utils/context_parser.py
lmstrix/utils/logging.py
lmstrix/utils/paths.py
lmstrix/utils/state.py
lmstrix-1.0.70.dist-info/METADATA
lmstrix-1.0.70.dist-info/WHEEL
lmstrix-1.0.70.dist-info/entry_points.txt
lmstrix-1.0.70.dist-info/licenses/LICENSE
lmstrix-1.0.70.dist-info/RECORD
