Metadata-Version: 2.4
Name: lmstrix
Version: 1.0.70
Summary: A toolkit for managing and testing LM Studio models with automatic context limit discovery
Project-URL: Homepage, https://github.com/twardoch/lmstrix
Project-URL: Documentation, https://github.com/twardoch/lmstrix#readme
Project-URL: Repository, https://github.com/twardoch/lmstrix.git
Project-URL: Issues, https://github.com/twardoch/lmstrix/issues
Project-URL: Changelog, https://github.com/twardoch/lmstrix/blob/main/CHANGELOG.md
Author-email: Adam Twardoch <adam+github@twardoch.com>
Maintainer-email: Adam Twardoch <adam+github@twardoch.com>
License: MIT License
License-File: LICENSE
Keywords: ai,cli,context,developer-tools,llm,lmstudio,optimization,testing
Classifier: Development Status :: 4 - Beta
Classifier: Intended Audience :: Developers
Classifier: License :: OSI Approved :: MIT License
Classifier: Operating System :: OS Independent
Classifier: Programming Language :: Python :: 3
Classifier: Programming Language :: Python :: 3.10
Classifier: Programming Language :: Python :: 3.11
Classifier: Programming Language :: Python :: 3.12
Classifier: Programming Language :: Python :: 3.13
Classifier: Topic :: Scientific/Engineering :: Artificial Intelligence
Classifier: Topic :: Software Development :: Libraries :: Python Modules
Classifier: Topic :: Software Development :: Quality Assurance
Classifier: Topic :: System :: Benchmark
Classifier: Typing :: Typed
Requires-Python: >=3.11
Requires-Dist: fire>=0.7.0
Requires-Dist: httpx>=0.24
Requires-Dist: hydra-core
Requires-Dist: lmstudio>=1.4.1
Requires-Dist: loguru>=0.7
Requires-Dist: omegaconf
Requires-Dist: pathvalidate
Requires-Dist: pydantic>=2.0
Requires-Dist: rich>=13.9.4
Requires-Dist: tenacity>=8.5.0
Requires-Dist: tiktoken>=0.5
Requires-Dist: toml-topl>=1.0.5
Requires-Dist: tomli>=2.0.1; python_version < '3.11'
Provides-Extra: dev
Requires-Dist: black>=23.0; extra == 'dev'
Requires-Dist: mypy>=1.0; extra == 'dev'
Requires-Dist: pre-commit>=3.0; extra == 'dev'
Requires-Dist: pytest-asyncio>=0.21; extra == 'dev'
Requires-Dist: pytest-cov>=4.0; extra == 'dev'
Requires-Dist: pytest-mock>=3.10; extra == 'dev'
Requires-Dist: pytest>=7.0; extra == 'dev'
Requires-Dist: ruff>=0.1.0; extra == 'dev'
Requires-Dist: setuptools>=68.0.0; extra == 'dev'
Provides-Extra: docs
Requires-Dist: myst-parser>=2.0; extra == 'docs'
Requires-Dist: sphinx-autodoc-typehints>=1.25; extra == 'docs'
Requires-Dist: sphinx-rtd-theme>=2.0; extra == 'docs'
Requires-Dist: sphinx>=7.0; extra == 'docs'
